Metadata-Version: 2.1
Name: pystencils-reco
Version: 0.2.0
Summary: A flexible reconstruction framework based on pystencils
Home-page: https://pyscaffold.org/
Author: Stephan Seitz
Author-email: stephan.seitz@fau.de
License: gpl3
Platform: any
Classifier: Development Status :: 4 - Beta
Classifier: Programming Language :: Python
Requires-Python: >=3.6
Provides-Extra: docs
Provides-Extra: testing
